[
  { "reportDetailId": 1001, "reportId": 101, "tagId": 1, "taskId": 100, "taskTitle": "두레이 API 연동 검토", "taskLink": "https://dooray.com/tasks/100", "done": "API 스펙 검토 및 샘플 호출", "workHours": 2, "performance": null, "createdAt": "2025-03-03T18:00:00.000Z", "createdMemberId": 1 },
  { "reportDetailId": 1002, "reportId": 101, "tagId": 2, "taskId": 101, "taskTitle": "데일리 슈크럼 UI 기획", "taskLink": "https://dooray.com/tasks/101", "done": "화면 와이어프레임 작성", "workHours": 3, "performance": "기획 문서 정리 완료", "createdAt": "2025-03-03T18:00:00.000Z", "createdMemberId": 1 },
  { "reportDetailId": 1003, "reportId": 102, "tagId": 1, "taskId": 102, "taskTitle": "인증 플로우 설계", "taskLink": "https://dooray.com/tasks/102", "done": "JWT 발급 플로우 정리", "workHours": 2.5, "performance": null, "createdAt": "2025-03-04T18:00:00.000Z", "createdMemberId": 1 },
  { "reportDetailId": 1004, "reportId": 102, "tagId": 3, "taskId": 103, "taskTitle": "PR 리뷰", "taskLink": "https://dooray.com/tasks/103", "done": "슈크럼 API PR 리뷰 2건", "workHours": 1, "performance": null, "createdAt": "2025-03-04T18:00:00.000Z", "createdMemberId": 1 },
  { "reportDetailId": 1005, "reportId": 201, "tagId": 1, "taskId": 100, "taskTitle": "두레이 API 연동 검토", "taskLink": "https://dooray.com/tasks/100", "done": "API 스펙 검토 및 샘플 호출\n\n인증 플로우 설계", "workHours": 4.5, "performance": null, "createdAt": "2025-03-05T03:00:00.000Z", "createdMemberId": 1 },
  { "reportDetailId": 1006, "reportId": 201, "tagId": 2, "taskId": 101, "taskTitle": "데일리 슈크럼 UI 기획", "taskLink": "https://dooray.com/tasks/101", "done": "화면 와이어프레임 작성", "workHours": 3, "performance": "기획 문서 정리 완료", "createdAt": "2025-03-05T03:00:00.000Z", "createdMemberId": 1 },
  { "reportDetailId": 1007, "reportId": 201, "tagId": 3, "taskId": 103, "taskTitle": "PR 리뷰", "taskLink": "https://dooray.com/tasks/103", "done": "슈크럼 API PR 리뷰 2건", "workHours": 1, "performance": null, "createdAt": "2025-03-05T03:00:00.000Z", "createdMemberId": 1 },
  { "reportDetailId": 1008, "reportId": 301, "tagId": 1, "taskId": 0, "taskTitle": "두레이 관련 업무", "taskLink": "#", "done": "API 검토, 인증 설계 등 통합", "workHours": 15, "performance": null, "createdAt": "2025-03-26T05:00:00.000Z", "createdMemberId": 1 },
  { "reportDetailId": 1009, "reportId": 301, "tagId": 2, "taskId": 0, "taskTitle": "슈크럼 관련 업무", "taskLink": "#", "done": "UI 기획, 개발 진행", "workHours": 20, "performance": null, "createdAt": "2025-03-26T05:00:00.000Z", "createdMemberId": 1 },
  { "reportDetailId": 1010, "reportId": 401, "tagId": 1, "taskId": 0, "taskTitle": "두레이·슈크럼 성과", "taskLink": "#", "done": "연간 성과 요약", "workHours": 100, "performance": "API 연동 및 기획 주도", "createdAt": "2025-03-08T10:00:00.000Z", "createdMemberId": 1 }
]
